README.md
requirements.txt
setup.py
fromconfig_mlflow/__init__.py
fromconfig_mlflow/log_artifacts.py
fromconfig_mlflow/log_params.py
fromconfig_mlflow/start_run.py
fromconfig_mlflow/version.py
fromconfig_mlflow.egg-info/PKG-INFO
fromconfig_mlflow.egg-info/SOURCES.txt
fromconfig_mlflow.egg-info/dependency_links.txt
fromconfig_mlflow.egg-info/entry_points.txt
fromconfig_mlflow.egg-info/requires.txt
fromconfig_mlflow.egg-info/top_level.txt
tests/__init__.py
tests/conftest.py
tests/unit/__init__.py
tests/unit/test_log_artifacts.py
tests/unit/test_log_params.py
tests/unit/test_start_run.py