Metadata-Version: 2.1
Name: fromconfig-mlflow
Version: 0.4.0
Summary: # FromConfig MlFlow <!-- {docsify-ignore} -->
Home-page: https://github.com/criteo/fromconfig-mlflow
Author: Criteo
License: UNKNOWN
Platform: UNKNOWN
Classifier: License :: OSI Approved :: Apache Software License
Classifier: Operating System :: OS Independent
Classifier: Programming Language :: Python :: 3
Classifier: Programming Language :: Python :: 3.6
Classifier: Intended Audience :: Developers
